carbon_ops/__init__.py
carbon_ops/config.py
carbon_ops/ledger.py
carbon_ops/pipeline.py
carbon_ops-0.1.0.dist-info/METADATA
carbon_ops-0.1.0.dist-info/WHEEL
carbon_ops-0.1.0.dist-info/top_level.txt
carbon_ops-0.1.0.dist-info/RECORD
