Metadata-Version: 2.4
Name: carbon-ops
Version: 0.1.0
Summary: Carbon Ops Guardrails — audit-ready carbon accounting for AI workloads
Author: Scarlet Moore
Requires-Python: >=3.11
Requires-Dist: fastapi<1.0,>=0.115
Requires-Dist: pydantic<3.0,>=2.6
Requires-Dist: google-cloud-pubsub>=2.19
Requires-Dist: google-cloud-bigquery>=3.15
Requires-Dist: google-cloud-storage>=2.15
Requires-Dist: google-cloud-functions>=1.15
Requires-Dist: google-crc32c>=1.5
Requires-Dist: pyyaml>=6.0
Requires-Dist: python-dotenv>=1.0
Requires-Dist: pynacl>=1.5
Requires-Dist: merklelib>=1.1
Requires-Dist: httpx>=0.27
Requires-Dist: tenacity>=8.4
Provides-Extra: dev
Requires-Dist: pytest>=8.3; extra == "dev"
Requires-Dist: pytest-cov>=5.0; extra == "dev"
Requires-Dist: ruff>=0.6; extra == "dev"
Requires-Dist: mypy>=1.12; extra == "dev"
Requires-Dist: types-pyyaml; extra == "dev"
Requires-Dist: pytest-asyncio>=0.24; extra == "dev"
Provides-Extra: docs
Requires-Dist: mkdocs-material>=9.5; extra == "docs"
Requires-Dist: mkdocstrings[python]>=0.25; extra == "docs"
